{"display":{"firstperson_lefthand":{"scale":[0.4,0.4,0.4],"translation":[-1.75,0,0.5]},"firstperson_righthand":{"scale":[0.4,0.4,0.4],"translation":[4.75,0,0.5]},"fixed":{"rotation":[-90,0,0],"scale":[2,2,2],"translation":[0,0,-16]},"ground":{"scale":[0.25,0.25,0.25],"translation":[0,3,0]},"gui":{"rotation":[30,-135,0],"scale":[0.45,0.45,0.45],"translation":[-2.5,-2.25,0]},"head":{"translation":[8,3.35,0]},"thirdperson_lefthand":{"rotation":[68,0,0],"scale":[0.375,0.375,0.375],"translation":[-3,1.5,-3.5]},"thirdperson_righthand":{"rotation":[68,0,0],"scale":[0.375,0.375,0.375],"translation":[3,1.5,-3.5]}},"elements":[{"faces":{"down":{"rotation":270,"texture":"#1","uv":[4.375,2,6.375,4]},"east":{"texture":"#1","uv":[2.25,4.375,4.25,4.625]},"north":{"texture":"#1","uv":[0.125,4.375,2.125,4.625]},"south":{"texture":"#1","uv":[0.125,4.375,2.125,4.625]},"up":{"rotation":90,"texture":"#1","uv":[4.375,0,6.375,2]}},"from":[-0.01018,14,-0.00732],"rotation":{"angle":0,"axis":"y","origin":[7.99857,10.71429,-0.00875]},"to":[15.98982,16,15.99268]},{"faces":{"down":{"rotation":180,"texture":"#1","uv":[0.625,7.75,0.375,7.5]},"east":{"texture":"#1","uv":[0.875,5.75,0.625,6.875]},"north":{"texture":"#1","uv":[0.875,5.75,1.125,6.875]},"south":{"texture":"#1","uv":[0.375,5.75,0.625,6.875]},"west":{"texture":"#1","uv":[0.375,5.75,0.125,6.875]}},"from":[11.98982,5,11.99268],"rotation":{"angle":0,"axis":"y","origin":[7.99857,10.71429,-0.00875]},"to":[13.98982,14,13.99268]},{"faces":{"down":{"rotation":180,"texture":"#1","uv":[0.625,7.5,0.375,7.75]},"east":{"texture":"#1","uv":[0.625,5.75,0.875,6.875]},"north":{"texture":"#1","uv":[0.625,5.75,0.375,6.875]},"south":{"texture":"#1","uv":[1.125,5.75,0.875,6.875]},"west":{"texture":"#1","uv":[0.125,5.75,0.375,6.875]}},"from":[11.98982,5,1.99268],"rotation":{"angle":0,"axis":"y","origin":[7.99857,10.71429,-0.00875]},"to":[13.98982,14,3.99268]},{"faces":{"down":{"rotation":90,"texture":"#1","uv":[0.625,7.75,0.375,7.5]},"east":{"texture":"#1","uv":[0.875,5.75,1.125,6.875]},"north":{"texture":"#1","uv":[0.375,5.75,0.125,6.875]},"south":{"texture":"#1","uv":[0.875,5.75,0.625,6.875]},"west":{"texture":"#1","uv":[0.375,5.75,0.625,6.875]}},"from":[-14.01018,5,11.99268],"rotation":{"angle":0,"axis":"y","origin":[7.99857,10.71429,-0.00875]},"to":[-12.01018,14,13.99268]},{"faces":{"down":{"texture":"#1","uv":[4.25,4.875,4,5.125]},"east":{"texture":"#1","uv":[1.125,5.75,0.875,6.875]},"north":{"texture":"#1","uv":[0.625,5.75,0.875,6.875]},"south":{"texture":"#1","uv":[0.125,5.75,0.375,6.875]},"west":{"texture":"#1","uv":[0.625,5.75,0.375,6.875]}},"from":[-14.01018,5,1.99268],"rotation":{"angle":0,"axis":"y","origin":[7.99857,10.71429,-0.00875]},"to":[-12.01018,14,3.99268]},{"faces":{"down":{"rotation":270,"texture":"#1","uv":[4.375,0,6.375,2]},"north":{"texture":"#1","uv":[2.25,4.375,4.25,4.625]},"south":{"texture":"#1","uv":[2.25,4.375,4.25,4.625]},"up":{"rotation":90,"texture":"#1","uv":[4.375,2,6.375,4]},"west":{"texture":"#1","uv":[0.125,4.375,2.125,4.625]}},"from":[-15.96268,14,-0.00732],"rotation":{"angle":0,"axis":"y","origin":[7.99857,10.71429,-0.00875]},"to":[0.03732,16,15.99268]},{"faces":{"down":{"rotation":180,"texture":"#1","uv":[5.625,7.75,7.25,6.5]},"east":{"rotation":90,"texture":"#1","uv":[7.125,0.375,7.75,1.625]},"north":{"texture":"#1","uv":[4.375,4.125,6,4.75]},"south":{"rotation":90,"texture":"#1","uv":[6.625,0,7.25,1.625]}},"from":[0,9,3],"rotation":{"angle":0,"axis":"y","origin":[12,9,3]},"to":[13,14,13]},{"faces":{"down":{"rotation":180,"texture":"#1","uv":[7.5,7.75,9.125,6.5]},"north":{"texture":"#1","uv":[6,4.125,4.375,4.75]},"south":{"rotation":90,"texture":"#1","uv":[6.625,0.375,7.25,2]},"west":{"rotation":90,"texture":"#1","uv":[7.125,0.375,7.75,1.625]}},"from":[-13,9,3],"rotation":{"angle":0,"axis":"y","origin":[-1,9,3]},"to":[0,14,13]},{"faces":{"down":{"texture":"#missing","uv":[0,0,7,0]},"east":{"texture":"#missing","uv":[0,0,0,1]},"north":{"texture":"#1","uv":[8.125,4.25,6.125,4.75]},"south":{"texture":"#1","uv":[6.125,4.25,8.125,4.75]},"up":{"texture":"#missing","uv":[0,0,7,0]},"west":{"texture":"#missing","uv":[0,0,0,1]}},"from":[0,16,15.975],"rotation":{"angle":0,"axis":"y","origin":[0,16,14.975]},"to":[14,20,15.975]},{"faces":{"east":{"texture":"#1","uv":[4.625,5.25,4.375,5.5]},"north":{"texture":"#1","uv":[4.375,5.25,4.625,5.5]},"south":{"texture":"#1","uv":[4.375,5.25,4.625,5.5]},"up":{"texture":"#1","uv":[4,4.875,4.25,5.125]},"west":{"texture":"#1","uv":[4.625,5.25,4.375,5.5]}},"from":[-16,16,14],"rotation":{"angle":0,"axis":"y","origin":[0,16,15]},"to":[-14,18,16]},{"faces":{"down":{"texture":"#missing","uv":[0,0,7,0]},"east":{"texture":"#missing","uv":[0,0,0,1]},"north":{"texture":"#1","uv":[6.125,4.25,8.125,4.75]},"south":{"texture":"#1","uv":[8.125,4.25,6.125,4.75]},"up":{"texture":"#missing","uv":[0,0,7,0]},"west":{"texture":"#missing","uv":[0,0,0,1]}},"from":[-14,16,15.975],"rotation":{"angle":0,"axis":"y","origin":[-14,16,14.975]},"to":[0,20,15.975]},{"faces":{"east":{"texture":"#1","uv":[4.5,5.25,4.375,5.5]},"north":{"texture":"#1","uv":[4.375,5.25,4.5,5.5]},"south":{"texture":"#1","uv":[4.375,5.25,4.5,5.5]},"up":{"texture":"#1","uv":[4,4.875,4.125,5]},"west":{"texture":"#1","uv":[4.5,5.25,4.375,5.5]}},"from":[-15,18,15],"rotation":{"angle":0,"axis":"y","origin":[0,18,15]},"to":[-14,20,16]},{"faces":{"east":{"texture":"#1","uv":[4.375,5.25,4.625,5.5]},"north":{"texture":"#1","uv":[4.625,5.25,4.375,5.5]},"south":{"texture":"#1","uv":[4.625,5.25,4.375,5.5]},"up":{"rotation":90,"texture":"#1","uv":[4,4.875,4.25,5.125]},"west":{"texture":"#1","uv":[4.375,5.25,4.625,5.5]}},"from":[14,16,14],"rotation":{"angle":0,"axis":"y","origin":[14.25,18,15.25]},"to":[16,18,16]},{"faces":{"east":{"texture":"#1","uv":[4.375,5.25,4.5,5.5]},"north":{"texture":"#1","uv":[4.5,5.25,4.375,5.5]},"south":{"texture":"#1","uv":[4.5,5.25,4.375,5.5]},"up":{"rotation":90,"texture":"#1","uv":[4,4.875,4.125,5]},"west":{"texture":"#1","uv":[4.375,5.25,4.5,5.5]}},"from":[14,18,15],"rotation":{"angle":0,"axis":"y","origin":[14.25,18,15.25]},"to":[15,20,16]},{"faces":{"down":{"rotation":90,"texture":"#1","uv":[0.375,7.75,0.5,7.875]},"east":{"texture":"#1","uv":[0.375,7,0.25,7.625]},"north":{"texture":"#1","uv":[0.25,7,0.375,7.625]},"south":{"texture":"#1","uv":[0.25,7,0.375,7.625]},"west":{"texture":"#1","uv":[0.375,7,0.25,7.625]}},"from":[-13.01018,0,2.99268],"rotation":{"angle":0,"axis":"y","origin":[7.99857,5.71429,-0.00875]},"to":[-12.01018,5,3.99268]},{"faces":{"down":{"rotation":90,"texture":"#1","uv":[0.375,7.75,0.5,7.875]},"east":{"texture":"#1","uv":[0.375,7,0.25,7.625]},"north":{"texture":"#1","uv":[0.25,7,0.375,7.625]},"south":{"texture":"#1","uv":[0.25,7,0.375,7.625]},"west":{"texture":"#1","uv":[0.375,7,0.25,7.625]}},"from":[11.98982,0,2.99268],"rotation":{"angle":0,"axis":"y","origin":[32.99857,5.71429,-0.00875]},"to":[12.98982,5,3.99268]},{"faces":{"down":{"rotation":90,"texture":"#1","uv":[0.375,7.75,0.5,7.875]},"east":{"texture":"#1","uv":[0.375,7,0.25,7.625]},"north":{"texture":"#1","uv":[0.25,7,0.375,7.625]},"south":{"texture":"#1","uv":[0.25,7,0.375,7.625]},"west":{"texture":"#1","uv":[0.375,7,0.25,7.625]}},"from":[-13.01018,0,11.99268],"rotation":{"angle":0,"axis":"y","origin":[7.99857,5.71429,8.99125]},"to":[-12.01018,5,12.99268]},{"faces":{"down":{"rotation":90,"texture":"#1","uv":[0.375,7.75,0.5,7.875]},"east":{"texture":"#1","uv":[0.375,7,0.25,7.625]},"north":{"texture":"#1","uv":[0.25,7,0.375,7.625]},"south":{"texture":"#1","uv":[0.25,7,0.375,7.625]},"west":{"texture":"#1","uv":[0.375,7,0.25,7.625]}},"from":[11.98982,0,11.99268],"rotation":{"angle":0,"axis":"y","origin":[32.99857,5.71429,8.99125]},"to":[12.98982,5,12.99268]},{"faces":{"down":{"texture":"#1","uv":[5.375,4.375,5.125,4.5]},"east":{"texture":"#1","uv":[5.125,4.375,5.25,4.5]},"north":{"texture":"#1","uv":[5.125,4.375,5.375,4.5]},"up":{"texture":"#1","uv":[5.375,4.375,5.125,4.5]},"west":{"texture":"#1","uv":[5.25,4.375,5.375,4.5]}},"from":[5,11,2],"rotation":{"angle":0,"axis":"y","origin":[5,11,2]},"to":[7,12,2.5]},{"faces":{"down":{"texture":"#1","uv":[5.125,4.375,5.375,4.5]},"east":{"texture":"#1","uv":[5.25,4.375,5.375,4.5]},"north":{"texture":"#1","uv":[5.375,4.375,5.125,4.5]},"up":{"texture":"#1","uv":[5.125,4.375,5.375,4.5]},"west":{"texture":"#1","uv":[5.125,4.375,5.25,4.5]}},"from":[-7,11,2],"rotation":{"angle":0,"axis":"y","origin":[-7,11,2]},"to":[-5,12,2.5]},{"faces":{"down":{"texture":"#1","uv":[4.625,4.625,5.875,4.75]},"east":{"texture":"#1","uv":[4.625,4.25,4.75,4.75]},"north":{"texture":"#1","uv":[5.875,4.25,4.625,4.75]},"up":{"texture":"#1","uv":[4.625,4.25,5.875,4.375]},"west":{"texture":"#1","uv":[5.75,4.25,5.875,4.75]}},"from":[-11,9,2.5],"rotation":{"angle":0,"axis":"y","origin":[-11,9,2]},"to":[-1,13,3]},{"faces":{"down":{"texture":"#1","uv":[5.875,4.625,4.625,4.75]},"east":{"texture":"#1","uv":[4.625,4.25,4.75,4.75]},"north":{"texture":"#1","uv":[4.625,4.25,5.875,4.75]},"up":{"texture":"#1","uv":[4.625,4.25,5.875,4.375]},"west":{"texture":"#1","uv":[5.75,4.25,5.875,4.75]}},"from":[1,9,2.5],"rotation":{"angle":0,"axis":"y","origin":[1,9,2]},"to":[11,13,3]}],"format_version":"1.21.6","texture_size":[64,64],"textures":{"1":"projecteden/decoration/dyeable/spooky_wooden_set_1"}}