{"display":{"firstperson_lefthand":{"rotation":[0,225,0],"scale":[0.4,0.4,0.4],"translation":[0,4.5,0]},"firstperson_righthand":{"rotation":[0,45,0],"scale":[0.2,0.2,0.2],"translation":[0.5,1.75,1.25]},"fixed":{"rotation":[-90,0,0],"scale":[0.8,0.8,0.8],"translation":[0,0,-6.5]},"ground":{"scale":[0.2,0.2,0.2]},"gui":{"rotation":[30,-135,0],"scale":[0.35,0.35,0.35],"translation":[0.25,-1.25,0]},"head":{"scale":[0.5,0.5,0.5],"translation":[0,10.4,0]},"thirdperson_lefthand":{"rotation":[75,45,0],"scale":[0.375,0.375,0.375],"translation":[0,2.5,0]},"thirdperson_righthand":{"rotation":[70,45,0],"scale":[0.2,0.2,0.2],"translation":[-0.25,0.75,1.75]}},"elements":[{"faces":{"down":{"rotation":180,"texture":"#0","uv":[7,7,10,16]},"east":{"rotation":90,"texture":"#0","uv":[4.5,7,7,16]},"north":{"rotation":180,"texture":"#0","uv":[10,7,7,2]},"south":{"texture":"#0","uv":[13,2,10,7]},"up":{"texture":"#0","uv":[12.5,7,15.5,16]},"west":{"rotation":270,"texture":"#0","uv":[10,7,12.5,16]}},"from":[2.5,0,-1],"name":"rotation","rotation":{"angle":0,"axis":"x","origin":[0,17,-2.75]},"to":[14.5,10,17]},{"faces":{"down":{"rotation":180,"texture":"#0","uv":[13.25,0.5,14.25,3.5]},"east":{"rotation":90,"texture":"#0","uv":[13,0.5,13.25,3.5]},"north":{"rotation":180,"texture":"#0","uv":[14.25,0.5,13.25,0]},"south":{"texture":"#0","uv":[15.25,0,14.25,0.5]},"up":{"texture":"#0","uv":[14.5,0.5,15.5,3.5]},"west":{"rotation":270,"texture":"#0","uv":[14.25,0.5,14.5,3.5]}},"from":[6.5,-1,11],"name":"rotation","rotation":{"angle":0,"axis":"x","origin":[0,17,-2.75]},"to":[10.5,0,17]},{"faces":{"down":{"texture":"#0","uv":[5.5,0,3.5,3]},"east":{"texture":"#0","uv":[0,3,1.5,7]},"north":{"texture":"#0","uv":[1.5,3,3.5,7]},"south":{"texture":"#0","uv":[5,3,7,7]},"up":{"texture":"#0","uv":[3.5,3,1.5,0]},"west":{"texture":"#0","uv":[3.5,3,5,7]}},"from":[4.5,4,-7],"name":"head","to":[12.5,12,-1]},{"faces":{"down":{"texture":"#0","uv":[6.25,0,6,0.5]},"east":{"texture":"#0","uv":[5.5,0.5,5.75,2]},"north":{"texture":"#0","uv":[5.75,0.5,6,2]},"south":{"texture":"#0","uv":[6.25,0.5,6.5,2]},"up":{"texture":"#0","uv":[6,0.5,5.75,0]},"west":{"texture":"#0","uv":[6,0.5,6.25,2]}},"from":[3.5,10,-5],"name":"head","to":[4.5,13,-4]},{"faces":{"down":{"texture":"#0","uv":[6.25,0,6,0.5]},"east":{"texture":"#0","uv":[5.5,0.5,5.75,2]},"north":{"texture":"#0","uv":[5.75,0.5,6,2]},"south":{"texture":"#0","uv":[6.25,0.5,6.5,2]},"up":{"texture":"#0","uv":[6,0.5,5.75,0]},"west":{"texture":"#0","uv":[6,0.5,6.25,2]}},"from":[12.5,10,-5],"name":"head","to":[13.5,13,-4]},{"faces":{"down":{"rotation":270,"texture":"#0","uv":[2,10,3,16]},"east":{"rotation":270,"texture":"#0","uv":[3,8,2,10]},"north":{"rotation":90,"texture":"#0","uv":[1,10,2,16]},"south":{"rotation":270,"texture":"#0","uv":[3,10,4,16]},"up":{"rotation":270,"texture":"#0","uv":[0,10,1,16]},"west":{"rotation":270,"texture":"#0","uv":[2,10,1,8]}},"from":[13.7,0,12],"name":"leg1","rotation":{"angle":-22.5,"axis":"y","origin":[13.7,2,14]},"to":[25.7,4,16]},{"faces":{"down":{"rotation":90,"texture":"#0","uv":[0,10,1,16]},"east":{"rotation":90,"texture":"#0","uv":[2,10,1,8]},"north":{"rotation":270,"texture":"#0","uv":[1,10,2,16]},"south":{"rotation":90,"texture":"#0","uv":[3,10,4,16]},"up":{"rotation":90,"texture":"#0","uv":[2,10,3,16]},"west":{"rotation":90,"texture":"#0","uv":[3,8,2,10]}},"from":[-8.7,0,12],"name":"leg2","rotation":{"angle":22.5,"axis":"y","origin":[3.3,2,14]},"to":[3.3,4,16]},{"faces":{"down":{"rotation":270,"texture":"#0","uv":[2,10,3,16]},"east":{"rotation":270,"texture":"#0","uv":[3,8,2,10]},"north":{"rotation":90,"texture":"#0","uv":[1,10,2,16]},"south":{"rotation":270,"texture":"#0","uv":[3,10,4,16]},"up":{"rotation":270,"texture":"#0","uv":[0,10,1,16]},"west":{"rotation":270,"texture":"#0","uv":[2,10,1,8]}},"from":[13.7,0,0],"name":"leg3","rotation":{"angle":22.5,"axis":"y","origin":[13.7,2,2]},"to":[25.7,4,4]},{"faces":{"down":{"rotation":90,"texture":"#0","uv":[0,10,1,16]},"east":{"rotation":90,"texture":"#0","uv":[2,10,1,8]},"north":{"rotation":270,"texture":"#0","uv":[1,10,2,16]},"south":{"rotation":90,"texture":"#0","uv":[3,10,4,16]},"up":{"rotation":90,"texture":"#0","uv":[2,10,3,16]},"west":{"rotation":90,"texture":"#0","uv":[3,8,2,10]}},"from":[-8.7,0,0],"name":"leg4","rotation":{"angle":-22.5,"axis":"y","origin":[3.3,2,2]},"to":[3.3,4,4]}],"texture_size":[64,32],"textures":{"0":"projecteden/decoration/plushies/mob/cow","particle":"projecteden/decoration/plushies/mob/cow"}}