{"display":{"firstperson_lefthand":{"translation":[3.75,4.25,-4.75]},"firstperson_righthand":{"translation":[3.75,4.25,-4.75]},"fixed":{"rotation":[-90,0,0],"scale":[2,2,2],"translation":[0,0,-16]},"ground":{"scale":[0.36,0.36,0.36]},"gui":{"rotation":[20,45,0],"translation":[0,3.75,0]},"head":{"scale":[2.5,2.5,2.5],"translation":[0,15.25,0]},"thirdperson_lefthand":{"rotation":[68.75,0,0],"scale":[0.51,0.51,0.51],"translation":[0,2,1.75]},"thirdperson_righthand":{"rotation":[68.75,0,0],"scale":[0.51,0.51,0.51],"translation":[0,2,1.75]}},"elements":[{"faces":{"down":{"texture":"#0","uv":[0,12,10,0]},"east":{"texture":"#0","uv":[0,14,12,15]},"north":{"texture":"#0","uv":[10,12,0,13]},"south":{"texture":"#0","uv":[0,13,10,14]},"up":{"texture":"#0","uv":[0,0,10,12]},"west":{"texture":"#0","uv":[0,15,12,16]}},"from":[3,0,2],"rotation":{"angle":0,"axis":"y","origin":[7,0,2]},"to":[13,1,14]},{"faces":{"down":{"texture":"#0","uv":[10,7,16,13]},"east":{"texture":"#0","uv":[10,0,16,7]},"north":{"texture":"#0","uv":[10,0,16,7]},"south":{"texture":"#0","uv":[10,0,16,7]},"up":{"texture":"#0","uv":[10,7,16,13]},"west":{"texture":"#0","uv":[10,0,16,7]}},"from":[5,1,5],"rotation":{"angle":0,"axis":"y","origin":[7,1,2]},"to":[11,8,11]}],"groups":[{"children":[0,1],"color":0,"name":"group","origin":[7,1,2]}],"textures":{"0":"projecteden/events/vulan24/water_lantern","particle":"projecteden/events/vulan24/water_lantern"}}